mdformat_wikilink/__init__.py
mdformat_wikilink/mdformat_plugin.py
mdformat_wikilink/mdit_wikilink_plugin.py
mdformat_wikilink-0.3.0.dist-info/LICENSE
mdformat_wikilink-0.3.0.dist-info/METADATA
mdformat_wikilink-0.3.0.dist-info/WHEEL
mdformat_wikilink-0.3.0.dist-info/entry_points.txt
mdformat_wikilink-0.3.0.dist-info/RECORD
